setup.py
Sites/__init__.py
nhentai_sites.egg-info/PKG-INFO
nhentai_sites.egg-info/SOURCES.txt
nhentai_sites.egg-info/dependency_links.txt
nhentai_sites.egg-info/not-zip-safe
nhentai_sites.egg-info/top_level.txt