Metadata-Version: 1.0
Name: nhentai-sites
Version: 1.2
Summary: Hentai manga scraper
Home-page: https://www.github.com/Alvixeon/nhentai-py
Author: Alvixeon
Author-email: remusername@gmail.com
License: MIT
Platform: UNKNOWN
